data_france/__init__.py
data_france/admin/__init__.py
data_france/admin/utils.py
data_france/apps.py
data_france/data/__init__.py
data_france/data/cantons.csv.lzma
data_france/data/circonscriptions_consulaires.csv.lzma
data_france/data/circonscriptions_legislatives.csv.lzma
data_france/data/codes_postaux.csv.lzma
data_france/data/codes_postaux_communes.csv.lzma
data_france/data/collectivites_departementales.csv.lzma
data_france/data/collectivites_regionales.csv.lzma
data_france/data/communes.csv.lzma
data_france/data/ctu.csv
data_france/data/departements.csv.lzma
data_france/data/deputes.csv.lzma
data_france/data/deputes_europeens.csv.lzma
data_france/data/elus_departementaux.csv.lzma
data_france/data/elus_municipaux.csv.lzma
data_france/data/elus_regionaux.csv.lzma
data_france/data/epci.csv.lzma
data_france/data/regions.csv.lzma
data_france/forms.py
data_france/management/__init__.py
data_france/management/commands/__init__.py
data_france/management/commands/update_data_france.py
data_france/migrations/0001_initial.py
data_france/migrations/0004_auto_20200327_0531.py
data_france/migrations/0005_auto_20200330_0827.py
data_france/migrations/0006_search.py
data_france/migrations/0007_ajout_departements_regions.py
data_france/migrations/0008_ajouts_verbose_names.py
data_france/migrations/0009_codes_postaux.py
data_france/migrations/0010_ameliore_recherche.py
data_france/migrations/0011_auto_20200416_0413.py
data_france/migrations/0012_collectivites_departementales_et_regionales.py
data_france/migrations/0013_cantons.py
data_france/migrations/0014_elumunicipal.py
data_france/migrations/0015_recherche_elus_municipaux.py
data_france/migrations/0016_auto_20210122_1031.py
data_france/migrations/0017_mairies.py
data_france/migrations/0018_elus_epci.py
data_france/migrations/0019_auto_20210209_0834.py
data_france/migrations/0020_elumunicipal_parrainage2017.py
data_france/migrations/0021_circonscriptionconsulaire.py
data_france/migrations/0022_auto_20210528_0804.py
data_france-0.15.0.dist-info/LICENSE
data_france-0.15.0.dist-info/METADATA
data_france-0.15.0.dist-info/WHEEL
data_france-0.15.0.dist-info/RECORD
