Metadata-Version: 2.3
Name: data-france
Version: 0.15.0
Summary: Paquet agrégeant des données administratives publiques pour en rendre l'utilisation facile.
License: GNU-GPL 3.0
Author: Salomé Cheysson
Author-email: salome@cheysson.fr
Requires-Python: >=3.10,<4.0
Classifier: Environment :: Web Environment
Classifier: Framework :: Django
Classifier: Intended Audience :: Developers
Classifier: License :: OSI Approved :: BSD License
Classifier: License :: OSI Approved :: GNU General Public License v3 or later (GPLv3+)
Classifier: License :: Other/Proprietary License
Classifier: Operating System :: OS Independent
Classifier: Programming Language :: Python
Classifier: Programming Language :: Python :: 3
Classifier: Programming Language :: Python :: 3.10
Classifier: Programming Language :: Python :: 3.11
Classifier: Programming Language :: Python :: 3.12
Classifier: Programming Language :: Python :: 3.13
Classifier: Programming Language :: Python :: 3 :: Only
Classifier: Programming Language :: Python :: 3.6
Classifier: Programming Language :: Python :: 3.7
Classifier: Programming Language :: Python :: 3.8
Classifier: Programming Language :: Python :: 3.9
Classifier: Topic :: Internet :: WWW/HTTP
Classifier: Topic :: Internet :: WWW/HTTP :: Dynamic Content
Requires-Dist: django (>=4.2,<5.0)
Requires-Dist: django-countries (>=7.3.1)
Requires-Dist: openpyxl (>=3.1.5,<4.0.0)
Requires-Dist: psycopg[binary] (>=3.2.6,<4.0.0)
Project-URL: Homepage, https://github.com/aktiur/data-france
